{
  "id": "86eb245337040a2b",
  "type": "experience",
  "content": {
    "agentId": "agent",
    "skillId": "mastery_skill",
    "mastery": {
      "level": "advanced",
      "successRate": 0.6666666666666666,
      "activations": 3,
      "successCount": 2,
      "lastUpdated": 1767105291379
    }
  },
  "metadata": {
    "type": "mastery",
    "agentId": "agent",
    "skillId": "mastery_skill",
    "level": "advanced",
    "successRate": 0.6666666666666666,
    "activations": 3
  },
  "tags": [
    "mastery",
    "agent",
    "mastery_skill",
    "advanced"
  ],
  "quality": "experimental",
  "vector": {
    "agentid": 1,
    "agent": 1,
    "skillid": 1,
    "mastery_skill": 1,
    "mastery": 1,
    "level": 1,
    "advanced": 1,
    "successrate": 1,
    "6666666666666666": 1,
    "activations": 1,
    "successcount": 1,
    "lastupdated": 1,
    "1767105291379": 1
  },
  "createdAt": 1767105291379,
  "lastAccessed": 1767105291379,
  "accessCount": 1,
  "usefulness": 0
}